data_expectations/__init__.py
data_expectations/errors.py
data_expectations/version.py
data_expectations/internals/__init__.py
data_expectations/internals/evaluate.py
data_expectations/internals/expectations.py
data_expectations/internals/models.py
data_expectations/internals/text.py
data_expectations-1.7.0.dist-info/LICENSE
data_expectations-1.7.0.dist-info/METADATA
data_expectations-1.7.0.dist-info/WHEEL
data_expectations-1.7.0.dist-info/top_level.txt
data_expectations-1.7.0.dist-info/RECORD
