Metadata-Version: 2.1
Name: data-expectations
Version: 1.7.0
Summary: Are your data meeting all your expecations
Home-page: https://github.com/joocer/data_expectations
Maintainer: Joocer
License-File: LICENSE
